dash_seqviz/SeqViz.py
dash_seqviz/__init__.py
dash_seqviz/_imports_.py
dash_seqviz/async-SeqViz.js
dash_seqviz/async-SeqViz.js.map
dash_seqviz/dash_seqviz.min.js
dash_seqviz/dash_seqviz.min.js.map
dash_seqviz/metadata.json
dash_seqviz/package-info.json
dash_seqviz-0.1.0.dist-info/licenses/LICENSE
dash_seqviz-0.1.0.dist-info/METADATA
dash_seqviz-0.1.0.dist-info/WHEEL
dash_seqviz-0.1.0.dist-info/top_level.txt
dash_seqviz-0.1.0.dist-info/RECORD
