Metadata-Version: 2.4
Name: dash_seqviz
Version: 0.1.0
Summary: A wrapper of the javascript DNA, RNA and protein sequence viewer
Author: Evan Rees <evanroyrees@gmail.com>
License: MIT
Classifier: Framework :: Dash
License-File: LICENSE
Dynamic: author
Dynamic: classifier
Dynamic: description
Dynamic: description-content-type
Dynamic: license
Dynamic: license-file
Dynamic: summary
